randsik/__init__.py
randsik/constants.py
randsik/midi/drums/blues/blues3.mid
randsik/midi/drums/blues/blues4.mid
randsik/midi/drums/blues/blues5.mid
randsik/midi/drums/blues/blues6.mid
randsik/midi/drums/funk/funk1.mid
randsik/midi/drums/funk/funk2.mid
randsik/midi/drums/funk/funk3.mid
randsik/midi/drums/funk/funk4.mid
randsik/midi/drums/funk/funk5.mid
randsik/midi/drums/funk/funk6.mid
randsik/midi/drums/funk/funk7.mid
randsik/midi/drums/funk/funk8.mid
randsik/midi/drums/rock/rock-fill1.mid
randsik/midi/drums/rock/rock1.mid
randsik/midi/drums/rock/rock10.mid
randsik/midi/drums/rock/rock11.mid
randsik/midi/drums/rock/rock12.mid
randsik/midi/drums/rock/rock13.mid
randsik/midi/drums/rock/rock14.mid
randsik/midi/drums/rock/rock2.mid
randsik/midi/drums/rock/rock3.mid
randsik/midi/drums/rock/rock4.mid
randsik/midi/drums/rock/rock5.mid
randsik/midi/drums/rock/rock6.mid
randsik/midi/drums/rock/rock7.mid
randsik/midi/drums/rock/rock8.mid
randsik/midi/drums/rock/rock9.mid
randsik/randsik.py
randsik/song_builder/__init__.py
randsik/song_builder/drums.py
randsik/song_builder/song.py
randsik-0.1.1.dist-info/WHEEL
randsik-0.1.1.dist-info/METADATA
randsik-0.1.1.dist-info/RECORD
